S3/S3.py
S3/__init__.py
s3_timeseries-0.1.0.dist-info/LICENSE
s3_timeseries-0.1.0.dist-info/METADATA
s3_timeseries-0.1.0.dist-info/WHEEL
s3_timeseries-0.1.0.dist-info/top_level.txt
s3_timeseries-0.1.0.dist-info/RECORD
