Metadata-Version: 2.1
Name: s3-timeseries
Version: 0.1.0
Summary: Official implementation of "Segment, Shuffle, and Stitch: A Simple Mechanism for Improving Time-Series Representations"
Home-page: https://github.com/shivam-grover/S3-TimeSeries
Author: Shivam Grover
Author-email: shivam.grover@queensu.com
Classifier: Programming Language :: Python :: 3
Classifier: License :: OSI Approved :: MIT License
Classifier: Operating System :: OS Independent
Requires-Python: >=3.6
License-File: LICENSE
Requires-Dist: torch >=1.8.0
